[
  {
    "raceTitle": "State Assembly District 37 - San Luis Obispo County Results",
    "Reporting": "0% (0 of 13) precincts reporting",
    "ReportingTime": "March 5, 2024, 9:56 p.m.",
    "candidates": [
      {
        "Name": "Gregg Hart",
        "Party": "Dem",
        "Votes": "2,491",
        "Percent": "53.9",
        "incumbent": true
      },
      {
        "Name": "Sari M. Domingues",
        "Party": "Rep",
        "Votes": "2,134",
        "Percent": "46.1",
        "incumbent": false
      }
    ]
  },
  {
    "raceTitle": "State Assembly District 37 - Districtwide Results",
    "Reporting": "46.9% (97 of 207) precincts reporting",
    "ReportingTime": "March 5, 2024, 11:02 p.m.",
    "candidates": [
      {
        "Name": "Gregg Hart",
        "Party": "Dem",
        "Votes": "34,179",
        "Percent": "63.3",
        "incumbent": true
      },
      {
        "Name": "Sari M. Domingues",
        "Party": "Rep",
        "Votes": "19,774",
        "Percent": "36.7",
        "incumbent": false
      }
    ]
  }
]