[
  {
    "raceTitle": "State Assembly District 13 - San Joaquin County Results",
    "Reporting": "100% (118 of 118) precincts reporting",
    "ReportingTime": "March 6, 2024, 1:23 a.m.",
    "candidates": [
      {
        "Name": "Rhodesia Ransom",
        "Party": "Dem",
        "Votes": "12,445",
        "Percent": "39.7",
        "incumbent": false
      },
      {
        "Name": "Edith Villapudua",
        "Party": "Dem",
        "Votes": "7,115",
        "Percent": "22.7",
        "incumbent": false
      },
      {
        "Name": "Denise Aguilar Mendez",
        "Party": "Rep",
        "Votes": "11,766",
        "Percent": "37.6",
        "incumbent": false
      }
    ]
  },
  {
    "raceTitle": "State Assembly District 13 - Districtwide Results",
    "Reporting": "100% (118 of 118) precincts reporting",
    "ReportingTime": "March 7, 2024, 6:09 p.m.",
    "candidates": [
      {
        "Name": "Rhodesia Ransom",
        "Party": "Dem",
        "Votes": "12,445",
        "Percent": "39.7",
        "incumbent": false
      },
      {
        "Name": "Edith Villapudua",
        "Party": "Dem",
        "Votes": "7,115",
        "Percent": "22.7",
        "incumbent": false
      },
      {
        "Name": "Denise Aguilar Mendez",
        "Party": "Rep",
        "Votes": "11,766",
        "Percent": "37.6",
        "incumbent": false
      }
    ]
  }
]