[
  {
    "raceTitle": "State Assembly District 27 - Madera County Results",
    "Reporting": "100% (23 of 23) precincts reporting",
    "ReportingTime": "March 13, 2024, 4:29 p.m.",
    "candidates": [
      {
        "Name": "Esmeralda Soria",
        "Party": "Dem",
        "Votes": "4,793",
        "Percent": "47.6",
        "incumbent": true
      },
      {
        "Name": "Joanna Garcia Rose",
        "Party": "Rep",
        "Votes": "5,280",
        "Percent": "52.4",
        "incumbent": false
      }
    ]
  },
  {
    "raceTitle": "State Assembly District 27 - Districtwide Results",
    "Reporting": "100% (704 of 704) precincts reporting",
    "ReportingTime": "March 20, 2024, 12:12 p.m.",
    "candidates": [
      {
        "Name": "Esmeralda Soria",
        "Party": "Dem",
        "Votes": "27,448",
        "Percent": "49.0",
        "incumbent": true
      },
      {
        "Name": "Joanna Garcia Rose",
        "Party": "Rep",
        "Votes": "28,570",
        "Percent": "51.0",
        "incumbent": false
      }
    ]
  }
]