{
  "raceTitle": "State Assembly District 19 - Districtwide Results",
  "Reporting": "100% (251 of 251) precincts reporting",
  "ReportingTime": "March 14, 2024, 4:29 p.m.",
  "candidates": [
    {
      "Name": "David E. Lee",
      "Party": "Dem",
      "Votes": "31,585",
      "Percent": "28.7",
      "incumbent": false
    },
    {
      "Name": "Catherine Stefani",
      "Party": "Dem",
      "Votes": "63,107",
      "Percent": "57.4",
      "incumbent": false
    },
    {
      "Name": "Nadia Flamenco",
      "Party": "Rep",
      "Votes": "7,955",
      "Percent": "7.2",
      "incumbent": false
    },
    {
      "Name": "Arjun Gustav Sodhani",
      "Party": "Rep",
      "Votes": "7,309",
      "Percent": "6.6",
      "incumbent": false
    }
  ]
}