[
  {
    "raceTitle": "State Senate District 1 - Shasta County Results",
    "Reporting": "20.6% (14 of 68) precincts reporting",
    "ReportingTime": "March 5, 2024, 11:23 p.m.",
    "candidates": [
      {
        "Name": "Megan Dahle",
        "Party": "Rep",
        "Votes": "489",
        "Percent": "73.5",
        "incumbent": false
      },
      {
        "Name": "David Fennell",
        "Party": "Rep",
        "Votes": "176",
        "Percent": "26.5",
        "incumbent": false
      }
    ]
  },
  {
    "raceTitle": "State Senate District 1 - Districtwide Results",
    "Reporting": "89.3% (602 of 674) precincts reporting",
    "ReportingTime": "March 5, 2024, 11:36 p.m.",
    "candidates": [
      {
        "Name": "Megan Dahle",
        "Party": "Rep",
        "Votes": "64,039",
        "Percent": "77.5",
        "incumbent": false
      },
      {
        "Name": "David Fennell",
        "Party": "Rep",
        "Votes": "18,562",
        "Percent": "22.5",
        "incumbent": false
      }
    ]
  }
]