[
  {
    "raceTitle": "State Assembly District 4 - Sonoma County Results",
    "Reporting": "100% (21 of 21) precincts reporting",
    "ReportingTime": "March 26, 2024, 3:05 p.m.",
    "candidates": [
      {
        "Name": "Cecilia M. Aguiar-Curry",
        "Party": "Dem",
        "Votes": "6,757",
        "Percent": "100.0",
        "incumbent": true
      }
    ]
  },
  {
    "raceTitle": "State Assembly District 4 - Districtwide Results",
    "Reporting": "100% (332 of 332) precincts reporting",
    "ReportingTime": "March 28, 2024, 12:09 p.m.",
    "candidates": [
      {
        "Name": "Cecilia M. Aguiar-Curry",
        "Party": "Dem",
        "Votes": "76,441",
        "Percent": "100.0",
        "incumbent": true
      }
    ]
  }
]