[
  {
    "raceTitle": "State Senate District 31 - Riverside County Results",
    "Reporting": "100% (244 of 244) precincts reporting",
    "ReportingTime": "March 21, 2024, 6:20 p.m.",
    "candidates": [
      {
        "Name": "Sabrina Cervantes",
        "Party": "Dem",
        "Votes": "39,152",
        "Percent": "39.3",
        "incumbent": false
      },
      {
        "Name": "Angelo Farooq",
        "Party": "Dem",
        "Votes": "14,725",
        "Percent": "14.8",
        "incumbent": false
      },
      {
        "Name": "Cynthia Navarro",
        "Party": "Rep",
        "Votes": "45,775",
        "Percent": "45.9",
        "incumbent": false
      }
    ]
  },
  {
    "raceTitle": "State Senate District 31 - Districtwide Results",
    "Reporting": "100% (249 of 249) precincts reporting",
    "ReportingTime": "March 21, 2024, 6:29 p.m.",
    "candidates": [
      {
        "Name": "Sabrina Cervantes",
        "Party": "Dem",
        "Votes": "39,777",
        "Percent": "39.4",
        "incumbent": false
      },
      {
        "Name": "Angelo Farooq",
        "Party": "Dem",
        "Votes": "14,930",
        "Percent": "14.8",
        "incumbent": false
      },
      {
        "Name": "Cynthia Navarro",
        "Party": "Rep",
        "Votes": "46,307",
        "Percent": "45.8",
        "incumbent": false
      }
    ]
  }
]