[
  {
    "raceTitle": "State Assembly District 59 - Orange County Results",
    "Reporting": "100% (452 of 452) precincts reporting",
    "ReportingTime": "March 6, 2024, 12:06 a.m.",
    "candidates": [
      {
        "Name": "Dave Obrand",
        "Party": "Dem",
        "Votes": "19,638",
        "Percent": "34.2",
        "incumbent": false
      },
      {
        "Name": "Phillip Chen",
        "Party": "Rep",
        "Votes": "37,856",
        "Percent": "65.8",
        "incumbent": true
      }
    ]
  },
  {
    "raceTitle": "State Assembly District 59 - Districtwide Results",
    "Reporting": "89% (467 of 525) precincts reporting",
    "ReportingTime": "March 6, 2024, 12:36 a.m.",
    "candidates": [
      {
        "Name": "Dave Obrand",
        "Party": "Dem",
        "Votes": "22,151",
        "Percent": "34.8",
        "incumbent": false
      },
      {
        "Name": "Phillip Chen",
        "Party": "Rep",
        "Votes": "41,462",
        "Percent": "65.2",
        "incumbent": true
      }
    ]
  }
]