[
  {
    "raceTitle": "State Assembly District 72 - Orange County Results",
    "Reporting": "100% (369 of 369) precincts reporting",
    "ReportingTime": "March 11, 2024, 5:07 p.m.",
    "candidates": [
      {
        "Name": "Dom Jones",
        "Party": "Dem",
        "Votes": "51,331",
        "Percent": "38.6",
        "incumbent": false
      },
      {
        "Name": "Diane Dixon",
        "Party": "Rep",
        "Votes": "81,677",
        "Percent": "61.4",
        "incumbent": true
      }
    ]
  },
  {
    "raceTitle": "State Assembly District 72 - Districtwide Results",
    "Reporting": "100% (369 of 369) precincts reporting",
    "ReportingTime": "March 11, 2024, 5:07 p.m.",
    "candidates": [
      {
        "Name": "Dom Jones",
        "Party": "Dem",
        "Votes": "51,331",
        "Percent": "38.6",
        "incumbent": false
      },
      {
        "Name": "Diane Dixon",
        "Party": "Rep",
        "Votes": "81,677",
        "Percent": "61.4",
        "incumbent": true
      }
    ]
  }
]