{
  "raceTitle": "State Assembly District 8 - Districtwide Results",
  "Reporting": "100% (208 of 208) precincts reporting",
  "ReportingTime": "March 11, 2024, 9:39 a.m.",
  "candidates": [
    {
      "Name": "Caleb Helsel",
      "Party": "Dem",
      "Votes": "32,159",
      "Percent": "30.0",
      "incumbent": false
    },
    {
      "Name": "George Radanovich",
      "Party": "Rep",
      "Votes": "39,284",
      "Percent": "36.7",
      "incumbent": false
    },
    {
      "Name": "David J. Tangipa",
      "Party": "Rep",
      "Votes": "32,379",
      "Percent": "30.2",
      "incumbent": false
    },
    {
      "Name": "Michael Matheson",
      "Party": "NPP",
      "Votes": "3,326",
      "Percent": "3.1",
      "incumbent": false
    }
  ]
}