[
  {
    "raceTitle": "State Assembly District 36 - Riverside County Results",
    "Reporting": "100% (177 of 177) precincts reporting",
    "ReportingTime": "March 5, 2024, 11:06 p.m.",
    "candidates": [
      {
        "Name": "Jose \"Joey\" Acuña Jr.",
        "Party": "Dem",
        "Votes": "3,586",
        "Percent": "17.5",
        "incumbent": false
      },
      {
        "Name": "Waymond Fermon",
        "Party": "Dem",
        "Votes": "2,026",
        "Percent": "9.9",
        "incumbent": false
      },
      {
        "Name": "Edgard Garcia",
        "Party": "Dem",
        "Votes": "3,475",
        "Percent": "17.0",
        "incumbent": false
      },
      {
        "Name": "Tomas Oliva",
        "Party": "Dem",
        "Votes": "1,241",
        "Percent": "6.1",
        "incumbent": false
      },
      {
        "Name": "Eric L. Rodriguez",
        "Party": "Dem",
        "Votes": "836",
        "Percent": "4.1",
        "incumbent": false
      },
      {
        "Name": "Jeff Gonzalez",
        "Party": "Rep",
        "Votes": "7,313",
        "Percent": "35.7",
        "incumbent": false
      },
      {
        "Name": "Kalin Morse",
        "Party": "Rep",
        "Votes": "2,006",
        "Percent": "9.8",
        "incumbent": false
      }
    ]
  },
  {
    "raceTitle": "State Assembly District 36 - Districtwide Results",
    "Reporting": "98% (483 of 493) precincts reporting",
    "ReportingTime": "March 6, 2024, 12:20 a.m.",
    "candidates": [
      {
        "Name": "Jose \"Joey\" Acuña Jr.",
        "Party": "Dem",
        "Votes": "5,179",
        "Percent": "18.5",
        "incumbent": false
      },
      {
        "Name": "Waymond Fermon",
        "Party": "Dem",
        "Votes": "2,384",
        "Percent": "8.5",
        "incumbent": false
      },
      {
        "Name": "Edgard Garcia",
        "Party": "Dem",
        "Votes": "4,615",
        "Percent": "16.5",
        "incumbent": false
      },
      {
        "Name": "Tomas Oliva",
        "Party": "Dem",
        "Votes": "2,170",
        "Percent": "7.7",
        "incumbent": false
      },
      {
        "Name": "Eric L. Rodriguez",
        "Party": "Dem",
        "Votes": "1,575",
        "Percent": "5.6",
        "incumbent": false
      },
      {
        "Name": "Jeff Gonzalez",
        "Party": "Rep",
        "Votes": "9,244",
        "Percent": "33.0",
        "incumbent": false
      },
      {
        "Name": "Kalin Morse",
        "Party": "Rep",
        "Votes": "2,875",
        "Percent": "10.3",
        "incumbent": false
      }
    ]
  }
]