[
  {
    "raceTitle": "State Assembly District 29 - Monterey County Results",
    "Reporting": "100% (121 of 121) precincts reporting",
    "ReportingTime": "March 15, 2024, 3:01 p.m.",
    "candidates": [
      {
        "Name": "Robert Rivas",
        "Party": "Dem",
        "Votes": "17,985",
        "Percent": "64.1",
        "incumbent": true
      },
      {
        "Name": "J.W. Paine",
        "Party": "Rep",
        "Votes": "10,073",
        "Percent": "35.9",
        "incumbent": false
      }
    ]
  },
  {
    "raceTitle": "State Assembly District 29 - Districtwide Results",
    "Reporting": "100% (199 of 199) precincts reporting",
    "ReportingTime": "March 22, 2024, 4:22 p.m.",
    "candidates": [
      {
        "Name": "Robert Rivas",
        "Party": "Dem",
        "Votes": "40,659",
        "Percent": "64.8",
        "incumbent": true
      },
      {
        "Name": "J.W. Paine",
        "Party": "Rep",
        "Votes": "22,102",
        "Percent": "35.2",
        "incumbent": false
      }
    ]
  }
]