{
  "raceTitle": "State Assembly District 13 - Districtwide Results",
  "Reporting": "100% (118 of 118) precincts reporting",
  "ReportingTime": "March 14, 2024, 12:30 p.m.",
  "candidates": [
    {
      "Name": "Rhodesia Ransom",
      "Party": "Dem",
      "Votes": "26,176",
      "Percent": "41.9",
      "incumbent": false
    },
    {
      "Name": "Edith Villapudua",
      "Party": "Dem",
      "Votes": "12,775",
      "Percent": "20.5",
      "incumbent": false
    },
    {
      "Name": "Denise Aguilar Mendez",
      "Party": "Rep",
      "Votes": "23,503",
      "Percent": "37.6",
      "incumbent": false
    }
  ]
}