[
  {
    "raceTitle": "State Assembly District 60 - Riverside County Results",
    "Reporting": "100% (139 of 139) precincts reporting",
    "ReportingTime": "March 7, 2024, 6:07 p.m.",
    "candidates": [
      {
        "Name": "Corey A Jackson",
        "Party": "Dem",
        "Votes": "14,289",
        "Percent": "52.3",
        "incumbent": true
      },
      {
        "Name": "Hector Diaz Nava",
        "Party": "Rep",
        "Votes": "5,427",
        "Percent": "19.9",
        "incumbent": false
      },
      {
        "Name": "Ron Edwards",
        "Party": "Rep",
        "Votes": "7,620",
        "Percent": "27.9",
        "incumbent": false
      }
    ]
  },
  {
    "raceTitle": "State Assembly District 60 - Districtwide Results",
    "Reporting": "100% (139 of 139) precincts reporting",
    "ReportingTime": "March 8, 2024, 3:41 p.m.",
    "candidates": [
      {
        "Name": "Corey A Jackson",
        "Party": "Dem",
        "Votes": "14,289",
        "Percent": "52.3",
        "incumbent": true
      },
      {
        "Name": "Hector Diaz Nava",
        "Party": "Rep",
        "Votes": "5,427",
        "Percent": "19.9",
        "incumbent": false
      },
      {
        "Name": "Ron Edwards",
        "Party": "Rep",
        "Votes": "7,620",
        "Percent": "27.9",
        "incumbent": false
      }
    ]
  }
]