[
  {
    "raceTitle": "U.S. House of Representatives District 10 - Contra Costa County Results",
    "Reporting": "100% (628 of 628) precincts reporting",
    "ReportingTime": "March 8, 2024, 4:03 p.m.",
    "candidates": [
      {
        "Name": "Mark DeSaulnier",
        "Party": "Dem",
        "Votes": "92,687",
        "Percent": "65.4",
        "incumbent": true
      },
      {
        "Name": "Nolan Lee Chen",
        "Party": "Rep",
        "Votes": "14,756",
        "Percent": "10.4",
        "incumbent": false
      },
      {
        "Name": "Katherine Piccinini",
        "Party": "Rep",
        "Votes": "27,517",
        "Percent": "19.4",
        "incumbent": false
      },
      {
        "Name": "Mohamed Elsherbini",
        "Party": "NPP",
        "Votes": "1,204",
        "Percent": "0.8",
        "incumbent": false
      },
      {
        "Name": "Joe Sweeney",
        "Party": "NPP",
        "Votes": "5,486",
        "Percent": "3.9",
        "incumbent": false
      }
    ]
  },
  {
    "raceTitle": "U.S. House of Representatives District 10 - Districtwide Results",
    "Reporting": "100% (645 of 645) precincts reporting",
    "ReportingTime": "March 11, 2024, 4:06 p.m.",
    "candidates": [
      {
        "Name": "Mark DeSaulnier",
        "Party": "Dem",
        "Votes": "93,583",
        "Percent": "65.3",
        "incumbent": true
      },
      {
        "Name": "Nolan Lee Chen",
        "Party": "Rep",
        "Votes": "15,021",
        "Percent": "10.5",
        "incumbent": false
      },
      {
        "Name": "Katherine Piccinini",
        "Party": "Rep",
        "Votes": "27,798",
        "Percent": "19.4",
        "incumbent": false
      },
      {
        "Name": "Mohamed Elsherbini",
        "Party": "NPP",
        "Votes": "1,245",
        "Percent": "0.9",
        "incumbent": false
      },
      {
        "Name": "Joe Sweeney",
        "Party": "NPP",
        "Votes": "5,575",
        "Percent": "3.9",
        "incumbent": false
      }
    ]
  }
]