[
  {
    "raceTitle": "U.S. House of Representatives District 49 - Orange County Results",
    "Reporting": "100% (194 of 194) precincts reporting",
    "ReportingTime": "March 11, 2024, 5:07 p.m.",
    "candidates": [
      {
        "Name": "Mike Levin",
        "Party": "Dem",
        "Votes": "27,527",
        "Percent": "43.5",
        "incumbent": true
      },
      {
        "Name": "Sheryl Adams",
        "Party": "Rep",
        "Votes": "1,993",
        "Percent": "3.1",
        "incumbent": false
      },
      {
        "Name": "Matt Gunderson",
        "Party": "Rep",
        "Votes": "17,646",
        "Percent": "27.9",
        "incumbent": false
      },
      {
        "Name": "Kate Monroe",
        "Party": "Rep",
        "Votes": "8,948",
        "Percent": "14.1",
        "incumbent": false
      },
      {
        "Name": "Margarita Wilkinson",
        "Party": "Rep",
        "Votes": "7,227",
        "Percent": "11.4",
        "incumbent": false
      }
    ]
  },
  {
    "raceTitle": "U.S. House of Representatives District 49 - Districtwide Results",
    "Reporting": "100% (472 of 472) precincts reporting",
    "ReportingTime": "March 12, 2024, 2:50 p.m.",
    "candidates": [
      {
        "Name": "Mike Levin",
        "Party": "Dem",
        "Votes": "91,240",
        "Percent": "50.8",
        "incumbent": true
      },
      {
        "Name": "Sheryl Adams",
        "Party": "Rep",
        "Votes": "4,378",
        "Percent": "2.4",
        "incumbent": false
      },
      {
        "Name": "Matt Gunderson",
        "Party": "Rep",
        "Votes": "46,456",
        "Percent": "25.8",
        "incumbent": false
      },
      {
        "Name": "Kate Monroe",
        "Party": "Rep",
        "Votes": "17,910",
        "Percent": "10.0",
        "incumbent": false
      },
      {
        "Name": "Margarita Wilkinson",
        "Party": "Rep",
        "Votes": "19,767",
        "Percent": "11.0",
        "incumbent": false
      }
    ]
  }
]