[
  {
    "raceTitle": "U.S. House of Representatives District 5 - Calaveras County Results",
    "Reporting": "100% (25 of 25) precincts reporting",
    "ReportingTime": "March 5, 2024, 10:50 p.m.",
    "candidates": [
      {
        "Name": "Michael J. \"Mike\" Barkley",
        "Party": "Dem",
        "Votes": "3,540",
        "Percent": "31.7",
        "incumbent": false
      },
      {
        "Name": "Tom McClintock",
        "Party": "Rep",
        "Votes": "6,470",
        "Percent": "57.9",
        "incumbent": true
      },
      {
        "Name": "Steve Wozniak",
        "Party": "NPP",
        "Votes": "1,171",
        "Percent": "10.5",
        "incumbent": false
      }
    ]
  },
  {
    "raceTitle": "U.S. House of Representatives District 5 - Districtwide Results",
    "Reporting": "100% (345 of 345) precincts reporting",
    "ReportingTime": "March 8, 2024, 2:52 p.m.",
    "candidates": [
      {
        "Name": "Michael J. \"Mike\" Barkley",
        "Party": "Dem",
        "Votes": "53,666",
        "Percent": "33.2",
        "incumbent": false
      },
      {
        "Name": "Tom McClintock",
        "Party": "Rep",
        "Votes": "93,715",
        "Percent": "58.0",
        "incumbent": true
      },
      {
        "Name": "Steve Wozniak",
        "Party": "NPP",
        "Votes": "14,212",
        "Percent": "8.8",
        "incumbent": false
      }
    ]
  }
]