[
  {
    "raceTitle": "U.S. House of Representatives District 18 - Santa Clara County Results",
    "Reporting": "100% (126 of 126) precincts reporting",
    "ReportingTime": "March 6, 2024, 6:24 p.m.",
    "candidates": [
      {
        "Name": "Luele N Kifle",
        "Party": "Dem",
        "Votes": "589",
        "Percent": "2.1",
        "incumbent": false
      },
      {
        "Name": "Zoe Lofgren",
        "Party": "Dem",
        "Votes": "15,839",
        "Percent": "55.8",
        "incumbent": true
      },
      {
        "Name": "Lawrence Milan",
        "Party": "Dem",
        "Votes": "659",
        "Percent": "2.3",
        "incumbent": false
      },
      {
        "Name": "Charlene Concepción Nijmeh",
        "Party": "Dem",
        "Votes": "2,588",
        "Percent": "9.1",
        "incumbent": false
      },
      {
        "Name": "Peter D. Hernandez",
        "Party": "Rep",
        "Votes": "8,705",
        "Percent": "30.7",
        "incumbent": false
      }
    ]
  },
  {
    "raceTitle": "U.S. House of Representatives District 18 - Districtwide Results",
    "Reporting": "100% (281 of 281) precincts reporting",
    "ReportingTime": "March 7, 2024, 1:52 p.m.",
    "candidates": [
      {
        "Name": "Luele N Kifle",
        "Party": "Dem",
        "Votes": "1,017",
        "Percent": "2.1",
        "incumbent": false
      },
      {
        "Name": "Zoe Lofgren",
        "Party": "Dem",
        "Votes": "24,952",
        "Percent": "52.4",
        "incumbent": true
      },
      {
        "Name": "Lawrence Milan",
        "Party": "Dem",
        "Votes": "1,459",
        "Percent": "3.1",
        "incumbent": false
      },
      {
        "Name": "Charlene Concepción Nijmeh",
        "Party": "Dem",
        "Votes": "4,432",
        "Percent": "9.3",
        "incumbent": false
      },
      {
        "Name": "Peter D. Hernandez",
        "Party": "Rep",
        "Votes": "15,799",
        "Percent": "33.2",
        "incumbent": false
      }
    ]
  }
]